NwalaTextUtils/__init__.py
NwalaTextUtils/scratch.py
NwalaTextUtils/textutils.py
tests/__init__.py
tests/test_generic.py
NwalaTextUtils-0.0.5.dist-info/LICENSE
NwalaTextUtils-0.0.5.dist-info/METADATA
NwalaTextUtils-0.0.5.dist-info/WHEEL
NwalaTextUtils-0.0.5.dist-info/top_level.txt
NwalaTextUtils-0.0.5.dist-info/RECORD
